MANIFEST.in
README.md
setup.cfg
setup.py
flashtorch/__init__.py
flashtorch.egg-info/PKG-INFO
flashtorch.egg-info/SOURCES.txt
flashtorch.egg-info/dependency_links.txt
flashtorch.egg-info/requires.txt
flashtorch.egg-info/top_level.txt
flashtorch/saliency/__init__.py
flashtorch/saliency/backprop.py
flashtorch/utils/__init__.py
flashtorch/utils/imagenet.py
flashtorch/utils/resources/__init__.py
flashtorch/utils/resources/imagenet_class_index.json