Metadata-Version: 2.1
Name: flashtorch
Version: 0.0.6
Summary: Visualisation toolkit for neural networks in PyTorch
Home-page: https://github.com/MisaOgura/flashtorch
Author: Misa Ogura
Author-email: misa.ogura01@gmail.com
License: UNKNOWN
Platform: UNKNOWN
Classifier: Programming Language :: Python :: 3
Classifier: License :: OSI Approved :: MIT License
Classifier: Operating System :: OS Independent
